stats101/__init__.py
stats101/confidence_interval.py
stats101-0.1.0.dist-info/AUTHORS.rst
stats101-0.1.0.dist-info/LICENSE
stats101-0.1.0.dist-info/METADATA
stats101-0.1.0.dist-info/WHEEL
stats101-0.1.0.dist-info/top_level.txt
stats101-0.1.0.dist-info/RECORD
