Metadata-Version: 2.1
Name: stats101
Version: 0.1.0
Summary: Making doing super-basic statistics as trivial as it should be.
Home-page: https://github.com/NapsterInBlue/stats101
Author: NapsterInBlue
Author-email: manifes7o@gmail.com
License: MIT license
Keywords: stats101
Platform: UNKNOWN
Classifier: Development Status :: 2 - Pre-Alpha
Classifier: Intended Audience :: Developers
Classifier: License :: OSI Approved :: MIT License
Classifier: Natural Language :: English
Classifier: Programming Language :: Python :: 3.5
Classifier: Programming Language :: Python :: 3.6
Classifier: Programming Language :: Python :: 3.7
